DidengAPI/__init__.py
DidengAPI/client.py
didengapi-0.1.1.dist-info/METADATA
didengapi-0.1.1.dist-info/WHEEL
didengapi-0.1.1.dist-info/top_level.txt
didengapi-0.1.1.dist-info/RECORD
